CODE_OF_CONDUCT.md
LICENSE
MANIFEST.in
README.md
setup.cfg
setup.py
versioneer.py
atb_api/__init__.py
atb_api/_version.py
atb_api/api.py
atb_api/atb_api.py
atb_api/atom.py
atb_api/base.py
atb_api/exceptions.py
atb_api/io.py
atb_api/mdanalysis.py
atb_api/molecule.py
atb_api/parameter.py
atb_api/utils.py
atb_api.egg-info/PKG-INFO
atb_api.egg-info/SOURCES.txt
atb_api.egg-info/dependency_links.txt
atb_api.egg-info/requires.txt
atb_api.egg-info/top_level.txt
atb_api/data/README.md
atb_api/data/look_and_say.dat
atb_api/templates/__init__.py
atb_api/templates/itp.py
atb_api/tests/__init__.py
atb_api/tests/conftest.py
atb_api/tests/datafiles.py
atb_api/tests/test_api.py
atb_api/tests/data/mol903922.json
atb_api/tests/data/mol903922_aa.itp
atb_api/tests/data/mol903922_aa_optimized.pdb
atb_api/tests/data/mol903922_aa_original.pdb
atb_api/tests/data/mol903922_aa_reordered.itp
atb_api/tests/data/mol903922_ua.itp
atb_api/tests/data/mol903922_ua_optimized.pdb
atb_api/tests/data/mol903922_ua_original.pdb
atb_api/tests/data/mol903922_ua_reordered.itp