Metadata-Version: 2.1
Name: atb-api
Version: 0.0.1
Summary: An API for ATB
Home-page: UNKNOWN
Author: Lily Wang
Author-email: lily.wang@anu.edu.au
License: MIT
Platform: Linux
Platform: Mac OS-X
Platform: Unix
Requires-Python: >=3.7
License-File: LICENSE
